tests/__init__.py
tests/test_contract.py
tests/test_creative.py
tests/test_deletion.py
tests/test_dictionary.py
tests/test_invoice.py
tests/test_notification.py
tests/test_organisation.py
tests/test_platform.py
tests/test_statistic.py
ozon_ord-0.0.1b1.dist-info/METADATA
ozon_ord-0.0.1b1.dist-info/WHEEL
ozon_ord-0.0.1b1.dist-info/top_level.txt
ozon_ord-0.0.1b1.dist-info/RECORD
