Metadata-Version: 2.1
Name: ozon-ord
Version: 0.0.1b1
Summary: Ozon ОРД API - Python
Home-page: https://github.com/frollow/ozon-ord
Author: Artem Frolov
Author-email: pypi-username@mail.ru
License: MIT
Keywords: ozon,ord,ozon-ord,api,sdk,python
Classifier: License :: OSI Approved :: MIT License
Classifier: Programming Language :: Python :: 3.8
Classifier: Programming Language :: Python :: 3.9
Classifier: Programming Language :: Python :: 3.10
Classifier: Programming Language :: Python :: 3.11
Classifier: Programming Language :: Python :: 3.12
Requires-Python: >=3.8
Requires-Dist: requests >=2.31.0
Requires-Dist: pydantic >=2.7.0
